<?xml version="1.0" encoding="utf-8"?>
<template>
  <transformations>
    <transformation query="copy" writer="FileIo" source="js" artifact="js"/>
    <transformation query="copy" writer="FileIo" source="images" artifact="images"/>
    <transformation query="copy" writer="FileIo" source="themes/old_ocean/css" artifact="css"/>
    <transformation query="copy" writer="FileIo" source="themes/frames/css" artifact="css"/>
    <transformation query="copy" writer="FileIo" source="themes/old_ocean/images" artifact="images"/>
    <transformation query="" writer="Search" source="" artifact="."/>
    <transformation query="" writer="xsl" source="themes/frames/frameset.xsl" artifact="index.html">
      <parameters>
        <variables><title>DocBlox</title></variables>
        <search>none</search>
      </parameters>
    </transformation>
    <transformation query="" writer="xsl" source="themes/frames/header.xsl" artifact="header.html">
      <parameters>
        <variables><title>DocBlox</title></variables>
        <search>xmljs</search>
      </parameters>
    </transformation>
    <transformation query="" writer="xsl" source="themes/frames/empty.xsl" artifact="side.html"/>
    <transformation query="" writer="xsl" source="themes/frames/index.xsl" artifact="content.html">
      <parameters><variables><title>Main</title></variables></parameters>
    </transformation>
    <transformation query="" writer="xsl" source="themes/frames/menu.xsl" artifact="menu.html">
      <parameters><variables><title>Menu</title></variables></parameters>
    </transformation>
    <transformation query="" writer="xsl" source="themes/frames/sidebar.xsl" artifact="sidebar.html">
      <parameters>
        <variables><title>Sidebar</title></variables>
        <search>xmljs</search>
      </parameters>
    </transformation>
    <transformation query="" writer="xsl" source="themes/frames/classgraph.xsl" artifact="graph.html">
      <parameters><variables><title>Class Diagram</title></variables></parameters>
    </transformation>
    <transformation query="" writer="Graph" source="Class" artifact="classes.svg" />
    <transformation query="/project/file/@path" writer="xsl" source="themes/frames/file.xsl" artifact="{$path}">
      <parameters><variables><title>File</title></variables></parameters>
    </transformation>
    <transformation query="" writer="xsl" source="themes/frames/markers.xsl" artifact="markers.html">
      <parameters>
        <variables>
          <title>Markers</title>
        </variables>
      </parameters>
    </transformation>
  </transformations>
</template>